pythonDockerizer/__init__.py
pythonDockerizer/dockerize.py
pythonDockerizer-0.2.dist-info/LICENSE
pythonDockerizer-0.2.dist-info/METADATA
pythonDockerizer-0.2.dist-info/WHEEL
pythonDockerizer-0.2.dist-info/entry_points.txt
pythonDockerizer-0.2.dist-info/top_level.txt
pythonDockerizer-0.2.dist-info/RECORD
